{
  "db": {
    "name": "db",
    "connector": "memory",
    "file": "data/data.json"
  },
  "newsAPI": {
    "name": "newsAPI",
    "baseURL": "https://newsapi.org/v2/top-headlines",
    "crud": false,
    "connector": "rest",
    "operations": [
      {
        "functions": {
          "getNews": [
            "name"
          ]
        },
        "template": {
          "method": "GET",
          "url": "https://newsapi.org/v2/top-headlines?country=ca&category=technology",
          "headers": {
            "accepts": "application/json",
            "content-type": "application/json",
            "x-api-key": "9a8d068cd73e4618bb1183d9cdb3f9dc"
          },
          "query": {
            "name": "{name}"
          },
          "responsePath": "$.articles.*"
        }
      }
    ]
  },

  "mongod": {
    "host": "ec2-35-182-61-225.ca-central-1.compute.amazonaws.com",
    "port": 27017,
    "url":"mongodb://ec2-35-182-61-225.ca-central-1.compute.amazonaws.com:27017/askSage", 
    "useNewUrlParser": "true",
    "database": "askSage",
    "password": "",
    "name": "mongod",
    "user": "",
    "connector": "mongodb"
  }




}
